{
  "_class": "shapePath",
  "booleanOperation": -1,
  "clippingMaskMode": 0,
  "do_objectID": "F7DEF68F-EA73-4A59-BCE1-71316DBB5CD1",
  "edited": true,
  "exportOptions": {
    "_class": "exportOptions",
    "exportFormats": [
    ],
    "includedLayerIds": [
    ],
    "layerOptions": 0,
    "shouldTrim": false
  },
  "frame": {
    "_class": "rect",
    "constrainProportions": false,
    "height": 1.867897228356238,
    "width": 1.845261031907931,
    "x": 8.705372981998366,
    "y": 55.3743500303234
  },
  "hasClippingMask": false,
  "isClosed": false,
  "isFixedToViewport": false,
  "isFlippedHorizontal": false,
  "isFlippedVertical": false,
  "isLocked": false,
  "isTemplate": false,
  "isVisible": true,
  "layerListExpandedType": 0,
  "name": "Fill 377",
  "nameIsFixed": false,
  "pointRadiusBehaviour": 1,
  "points": [
    {
      "_class": "curvePoint",
      "cornerRadius": 0,
      "cornerStyle": 0,
      "curveFrom": "{0.66810375970922098, 0.03627071588742381}",
      "curveMode": 4,
      "curveTo": "{0.8111729490731977, 0.14601979463111875}",
      "hasCurveFrom": true,
      "hasCurveTo": false,
      "point": "{0.8111729490731977, 0.14601979463111875}"
    },
    {
      "_class": "curvePoint",
      "cornerRadius": 0,
      "cornerStyle": 0,
      "curveFrom": "{0.074149852349689668, 0.09087757457940733}",
      "curveMode": 3,
      "curveTo": "{0.48113834179039044, -0.037073790394948777}",
      "hasCurveFrom": true,
      "hasCurveTo": true,
      "point": "{0.30013414009506034, 0.019674513735936833}"
    },
    {
      "_class": "curvePoint",
      "cornerRadius": 0,
      "cornerStyle": 0,
      "curveFrom": "{0.027002051309286977, 0.56520773929606505}",
      "curveMode": 4,
      "curveTo": "{-0.056454975819696551, 0.33286090917526445}",
      "hasCurveFrom": true,
      "hasCurveTo": true,
      "point": "{0.023750478823741965, 0.55664195754045853}"
    },
    {
      "_class": "curvePoint",
      "cornerRadius": 0,
      "cornerStyle": 0,
      "curveFrom": "{0.083362641058735157, 0.87196979841868827}",
      "curveMode": 4,
      "curveTo": "{0.030795552542425393, 0.57377352105166957}",
      "hasCurveFrom": true,
      "hasCurveTo": true,
      "point": "{0.034589053775559958, 0.5818039414475501}"
    },
    {
      "_class": "curvePoint",
      "cornerRadius": 0,
      "cornerStyle": 0,
      "curveFrom": "{0.861030393851552, 0.89391961416742571}",
      "curveMode": 3,
      "curveTo": "{0.39876517215658602, 1.0871850650282759}",
      "hasCurveFrom": true,
      "hasCurveTo": true,
      "point": "{0.69086476710803602, 0.9651226750108981}"
    },
    {
      "_class": "curvePoint",
      "cornerRadius": 0,
      "cornerStyle": 0,
      "curveFrom": "{1.0106027281866188, 0.40031644050065868}",
      "curveMode": 3,
      "curveTo": "{0.98567400579744158, 0.74615987888323043}",
      "hasCurveFrom": true,
      "hasCurveTo": true,
      "point": "{0.99868029573961781, 0.56146020977798683}"
    },
    {
      "_class": "curvePoint",
      "cornerRadius": 0,
      "cornerStyle": 0,
      "curveFrom": "{0.8111729490731977, 0.14601979463111875}",
      "curveMode": 4,
      "curveTo": "{0.94123584849499431, 0.245597007540033}",
      "hasCurveFrom": false,
      "hasCurveTo": true,
      "point": "{0.8111729490731977, 0.14601979463111875}"
    }
  ],
  "resizingConstraint": 63,
  "resizingType": 0,
  "rotation": 0,
  "shouldBreakMaskChain": false,
  "style": {
    "_class": "style",
    "blur": {
      "_class": "blur",
      "center": "{0.5, 0.5}",
      "isEnabled": false,
      "motionAngle": 0,
      "radius": 10,
      "saturation": 1,
      "type": 0
    },
    "borderOptions": {
      "_class": "borderOptions",
      "dashPattern": [
      ],
      "isEnabled": true,
      "lineCapStyle": 0,
      "lineJoinStyle": 0
    },
    "borders": [
    ],
    "colorControls": {
      "_class": "colorControls",
      "brightness": 0,
      "contrast": 1,
      "hue": 0,
      "isEnabled": false,
      "saturation": 1
    },
    "contextSettings": {
      "_class": "graphicsContextSettings",
      "blendMode": 0,
      "opacity": 1
    },
    "do_objectID": "78A1F4E3-ED3F-42CA-B526-AFD6DB9B345F",
    "endMarkerType": 0,
    "fills": [
      {
        "_class": "fill",
        "color": {
          "_class": "color",
          "alpha": 1,
          "blue": 0.278,
          "green": 0.392,
          "red": 0.894
        },
        "contextSettings": {
          "_class": "graphicsContextSettings",
          "blendMode": 0,
          "opacity": 1
        },
        "fillType": 0,
        "gradient": {
          "_class": "gradient",
          "elipseLength": 0,
          "from": "{0.5, 0}",
          "gradientType": 0,
          "stops": [
            {
              "_class": "gradientStop",
              "color": {
                "_class": "color",
                "alpha": 1,
                "blue": 1,
                "green": 1,
                "red": 1
              },
              "position": 0
            },
            {
              "_class": "gradientStop",
              "color": {
                "_class": "color",
                "alpha": 1,
                "blue": 0,
                "green": 0,
                "red": 0
              },
              "position": 1
            }
          ],
          "to": "{0.5, 1}"
        },
        "isEnabled": true,
        "noiseIndex": 0,
        "noiseIntensity": 0,
        "patternFillType": 1,
        "patternTileScale": 1
      }
    ],
    "innerShadows": [
    ],
    "miterLimit": 10,
    "shadows": [
    ],
    "startMarkerType": 0,
    "windingRule": 1
  }
}